swidget/__init__.py
swidget/cli.py
swidget/discovery.py
swidget/exceptions.py
swidget/provision.py
swidget/py.typed
swidget/swidgetdevice.py
swidget/swidgetdimmer.py
swidget/swidgetoutlet.py
swidget/swidgetswitch.py
swidget/swidgettimerswitch.py
swidget/websocket.py
python_swidget-1.4.0.dist-info/METADATA
python_swidget-1.4.0.dist-info/WHEEL
python_swidget-1.4.0.dist-info/entry_points.txt
python_swidget-1.4.0.dist-info/RECORD
