Metadata-Version: 2.4
Name: python-swidget
Version: 1.4.0
Summary: Python API for Swidget smart devices
License: GPL-3.0-or-later
Author: Swidget
Requires-Python: >=3.8,<4.0
Classifier: License :: OSI Approved :: GNU General Public License v3 or later (GPLv3+)
Classifier: Programming Language :: Python :: 3
Classifier: Programming Language :: Python :: 3.8
Classifier: Programming Language :: Python :: 3.9
Classifier: Programming Language :: Python :: 3.10
Classifier: Programming Language :: Python :: 3.11
Classifier: Programming Language :: Python :: 3.12
Classifier: Programming Language :: Python :: 3.13
Classifier: Programming Language :: Python :: 3.14
Provides-Extra: docs
Requires-Dist: aiohttp (>=3.8.1)
Requires-Dist: anyio
Requires-Dist: asyncclick (>=8)
Requires-Dist: importlib-metadata
Requires-Dist: m2r (>=0,<1) ; extra == "docs"
Requires-Dist: mistune (<2.0.0) ; extra == "docs"
Requires-Dist: pydantic (>=2,<3)
Requires-Dist: requests (==2.32.5)
Requires-Dist: sphinx (>=4,<5) ; extra == "docs"
Requires-Dist: sphinx_rtd_theme (>=0,<1) ; extra == "docs"
Requires-Dist: sphinxcontrib-programoutput (>=0,<1) ; extra == "docs"
Requires-Dist: ssdp (==1.1.1)
Requires-Dist: types-requests (>=2.32.0,<3.0.0)
Requires-Dist: urllib3 (==2.5.0)
Project-URL: Repository, https://github.com/swidget/python-swidget
